engine/__init__.py
engine/cli/__init__.py
engine/cli/auth.py
engine/cli/experiment.py
engine/cli/project.py
engine/connections/__init__.py
engine/connections/callisto.py
engine/connections/dione.py
engine/connections/europa.py
engine/connections/neso.py
engine/grain.py
engine/libs/__init__.py
engine/libs/config.py
engine/libs/hub.py
engine/libs/inquirer.py
engine/libs/utils.py
granular_engine-0.2.26.dist-info/METADATA
granular_engine-0.2.26.dist-info/WHEEL
granular_engine-0.2.26.dist-info/entry_points.txt
granular_engine-0.2.26.dist-info/RECORD
