Metadata-Version: 2.1
Name: granular-engine
Version: 0.2.26
Summary: Experiment tracking for GeoSpatial Machine Learning on GeoEngine
Home-page: https://github.com/granularai/engine
License: MIT
Author: Sagar Verma
Author-email: sagar@granular.ai
Requires-Python: >=3.7.0,<4.0.0
Classifier: Intended Audience :: Developers
Classifier: License :: OSI Approved :: MIT License
Classifier: Natural Language :: English
Classifier: Programming Language :: Python :: 3
Classifier: Programming Language :: Python :: 3.7
Classifier: Programming Language :: Python :: 3.8
Classifier: Programming Language :: Python :: 3.9
Classifier: Programming Language :: Python :: 3.10
Classifier: Programming Language :: Python :: 3.11
Classifier: Programming Language :: Python :: 3.10
Classifier: Programming Language :: Python :: 3.7
Classifier: Programming Language :: Python :: 3.8
Classifier: Programming Language :: Python :: 3.9
Requires-Dist: addict (>=2.4.0,<3.0.0)
Requires-Dist: appdirs (>=1.4.4,<2.0.0)
Requires-Dist: click (>=8.1.3,<9.0.0)
Requires-Dist: colorama (>=0.4.6,<0.5.0)
Requires-Dist: inquirerpy (>=0.3.4,<0.4.0)
Requires-Dist: keyring (>=23.11.0,<24.0.0)
Requires-Dist: keyrings-alt (>=4.2.0,<5.0.0)
Requires-Dist: passlib (>=1.7.4,<2.0.0)
Requires-Dist: tabulate (>=0.9.0,<0.10.0)
Requires-Dist: yacs (>=0.1.8,<0.2.0)
Requires-Dist: yapf (>=0.33.0,<0.34.0)
Project-URL: Repository, https://github.com/granularai/engine
